{"country":"United States","distributed_by":"Universal Pictures","Plot":"Eddie Macon (Schneider) was wrongly convicted of a crime. While performing at a prison rodeo in Huntsville, Texas, he escapes and heads for the border, hoping to join his family in Mexico. Marzack (Douglas) is a cop in hot pursuit of Eddie, determined to put him back in jail. Eddie has no transportation, so he takes the journey on foot. He ends up in the woods, where he is nearly killed. He meets Jilly Buck, a bored rich girl who agrees to help him because it's \"just a slow Wednesday.\"","language":"English","cinematography":"James A. Cotner","directed_by":"Jeff Kanew","release_dates":"March 23, 1983 (1983-03-23)|||||","produced_by":"Martin Bregman and Louis A. Stroller, Peter Saphier (executive producer)","starring":"Kirk Douglas John Schneider Lee Purcell","running_time":"95 minutes","eddie_macon's_run":"Original movie poster","music_by":"Norton Buffalo and Mike Hinton","edited_by":"Jeff Kanew","written_by":"Jeff Kanew"}