{"country":"United States","distributed_by":"Warner Bros.","DVD release":"MGM released a full screen DVD in 2003. Image Entertainment released a new DVD of the film, as well as a Blu-ray of the film on January 18, 2011.","Plot":"Ray Macklin is obsessed with his own mortality. When a close friend suddenly dies of a heart attack at a barbecue, Ray becomes convinced that every ache, pain and twinge he experiences is a sign of his own impending death. His unjustified fears lead him into ever more extensive hypochondria.","language":"English","box_office":"$31,000 US","cinematography":"Ian Wilson","directed_by":"David Leland","release_dates":"April 21, 1989 (1989-04-21)|||||","produced_by":"Ben Myron Garth Thomas George Harrison Denis O'Brien","starring":"Jeff Daniels|Melanie Mayron|Michael Tucker|Kathleen York|","running_time":"96 minutes","music_by":"Carter Burwell","External links":"","edited_by":"Lee Percy","written_by":"Joe Eszterhas"}